pylintxml/main.py
pylintxml/examples/books/.lintxml
pylintxml/examples/books/sample_fail.xml
pylintxml/examples/books/sample_ok.xml
pylintxml/examples/qt/.lintxml
pylintxml/examples/qt/sample.xml
pylintxml-0.0.6.dist-info/METADATA
pylintxml-0.0.6.dist-info/WHEEL
pylintxml-0.0.6.dist-info/entry_points.txt
pylintxml-0.0.6.dist-info/top_level.txt
pylintxml-0.0.6.dist-info/RECORD
