Metadata-Version: 2.1
Name: pylintxml
Version: 0.0.6
Summary: XML linter
Home-page: UNKNOWN
Author: BPL.
Author-email: 
License: MIT
Platform: UNKNOWN
Requires-Python: >=3.6.0
Requires-Dist: lxml (==4.3.4)
Requires-Dist: demjson (==2.2.4)
